syncwave/__init__.py
syncwave/io.py
syncwave/py.typed
syncwave/syncwave.py
syncwave/watcher.py
syncwave-0.1.4.dist-info/WHEEL
syncwave-0.1.4.dist-info/METADATA
syncwave-0.1.4.dist-info/RECORD
