Metadata-Version: 2.3
Name: syncwave
Version: 0.1.4
Summary: Make your code reactive; Turn plain JSONs into a live data store, two-way synced with Python objects.
Keywords: 
Author: Lucas Iannitello
Author-email: Lucas Iannitello <lucas.iannitello@protonmail.com>
License: MIT License
Requires-Dist: pydantic>=2.11.7
Requires-Dist: watchdog>=6.0.0
Requires-Python: >=3.9
Project-URL: Homepage, https://github.com/iannitello/syncwave
Project-URL: Issues, https://github.com/iannitello/syncwave/issues
Project-URL: Repository, https://github.com/iannitello/syncwave
